Math/Statistics.py
Math/__init__.py
TimeSeriesAnalysis/Chart.py
TimeSeriesAnalysis/Model.py
TimeSeriesAnalysis/ProcessData.py
TimeSeriesAnalysis/__init__.py
TimesML-0.0.7.dist-info/LICENSE
TimesML-0.0.7.dist-info/METADATA
TimesML-0.0.7.dist-info/WHEEL
TimesML-0.0.7.dist-info/top_level.txt
TimesML-0.0.7.dist-info/RECORD
