Metadata-Version: 2.1
Name: TimesML
Version: 0.0.7
Summary: This package is used for time series data analysis. Correct internal errors of functions, such as Statistics.normalized_mean_squard_error, Statistics.coefficient_of_determination.
Home-page: https://github.com/leodflag/TimesML
Author: leodflag
Author-email: lovedoglion5@gmail.com
License: UNKNOWN
Platform: UNKNOWN
Classifier: Programming Language :: Python :: 3
Classifier: License :: OSI Approved :: MIT License
Classifier: Intended Audience :: Science/Research
Requires-Python: >=3.6
